{"stats": [{"deaths": 38.0, "total_d": 6464.0, "date": "2020-06-23"}, {"deaths": 3.0, "total_d": 6426.0, "date": "2020-06-22"}, {"deaths": 4.0, "total_d": 6423.0, "date": "2020-06-21"}, {"deaths": 20.0, "total_d": 6419.0, "date": "2020-06-20"}, {"deaths": 38.0, "total_d": 6399.0, "date": "2020-06-19"}, {"deaths": 42.0, "total_d": 6361.0, "date": "2020-06-18"}, {"deaths": 43.0, "total_d": 6319.0, "date": "2020-06-17"}, {"deaths": 33.0, "total_d": 6276.0, "date": "2020-06-16"}, {"deaths": 28.0, "total_d": 6243.0, "date": "2020-06-15"}, {"deaths": 4.0, "total_d": 6215.0, "date": "2020-06-14"}, {"deaths": 49.0, "total_d": 6211.0, "date": "2020-06-13"}, {"deaths": 49.0, "total_d": 6162.0, "date": "2020-06-12"}, {"deaths": 51.0, "total_d": 6113.0, "date": "2020-06-11"}, {"deaths": 48.0, "total_d": 6062.0, "date": "2020-06-10"}, {"deaths": 61.0, "total_d": 6014.0, "date": "2020-06-09"}, {"deaths": 10.0, "total_d": 5953.0, "date": "2020-06-08"}, {"deaths": 12.0, "total_d": 5943.0, "date": "2020-06-07"}, {"deaths": 33.0, "total_d": 5931.0, "date": "2020-06-06"}, {"deaths": 66.0, "total_d": 5898.0, "date": "2020-06-05"}, {"deaths": 90.0, "total_d": 5832.0, "date": "2020-06-04"}, {"deaths": 75.0, "total_d": 5742.0, "date": "2020-06-03"}, {"deaths": 100.0, "total_d": 5667.0, "date": "2020-06-02"}, {"deaths": 12.0, "total_d": 5567.0, "date": "2020-06-01"}, {"deaths": 18.0, "total_d": 5555.0, "date": "2020-05-31"}, {"deaths": 73.0, "total_d": 5537.0, "date": "2020-05-30"}, {"deaths": 91.0, "total_d": 5464.0, "date": "2020-05-29"}, {"deaths": 108.0, "total_d": 5373.0, "date": "2020-05-28"}, {"deaths": 102.0, "total_d": 5265.0, "date": "2020-05-27"}, {"deaths": 17.0, "total_d": 5163.0, "date": "2020-05-26"}, {"deaths": 10.0, "total_d": 5146.0, "date": "2020-05-25"}, {"deaths": 24.0, "total_d": 5136.0, "date": "2020-05-24"}, {"deaths": 102.0, "total_d": 5112.0, "date": "2020-05-23"}, {"deaths": 141.0, "total_d": 5010.0, "date": "2020-05-22"}, {"deaths": 99.0, "total_d": 4869.0, "date": "2020-05-21"}, {"deaths": 142.0, "total_d": 4770.0, "date": "2020-05-20"}, {"deaths": 113.0, "total_d": 4628.0, "date": "2020-05-19"}, {"deaths": 20.0, "total_d": 4515.0, "date": "2020-05-18"}, {"deaths": 15.0, "total_d": 4495.0, "date": "2020-05-17"}, {"deaths": 58.0, "total_d": 4480.0, "date": "2020-05-16"}, {"deaths": 134.0, "total_d": 4422.0, "date": "2020-05-15"}, {"deaths": 194.0, "total_d": 4288.0, "date": "2020-05-14"}, {"deaths": 180.0, "total_d": 4094.0, "date": "2020-05-13"}, {"deaths": 82.0, "total_d": 3914.0, "date": "2020-05-12"}, {"deaths": 26.0, "total_d": 3832.0, "date": "2020-05-11"}, {"deaths": 27.0, "total_d": 3806.0, "date": "2020-05-10"}, {"deaths": 64.0, "total_d": 3779.0, "date": "2020-05-09"}, {"deaths": 126.0, "total_d": 3715.0, "date": "2020-05-08"}, {"deaths": 244.0, "total_d": 3589.0, "date": "2020-05-07"}, {"deaths": 166.0, "total_d": 3345.0, "date": "2020-05-06"}, {"deaths": 341.0, "total_d": 3179.0, "date": "2020-05-05"}, {"deaths": 118.0, "total_d": 2838.0, "date": "2020-05-04"}, {"deaths": 25.0, "total_d": 2720.0, "date": "2020-05-03"}, {"deaths": 60.0, "total_d": 2695.0, "date": "2020-05-02"}, {"deaths": 160.0, "total_d": 2635.0, "date": "2020-05-01"}, {"deaths": 102.0, "total_d": 2475.0, "date": "2020-04-30"}, {"deaths": 327.0, "total_d": 2373.0, "date": "2020-04-29"}, {"deaths": 160.0, "total_d": 2046.0, "date": "2020-04-28"}, {"deaths": 70.0, "total_d": 1886.0, "date": "2020-04-27"}, {"deaths": 23.0, "total_d": 1816.0, "date": "2020-04-26"}, {"deaths": 46.0, "total_d": 1793.0, "date": "2020-04-25"}, {"deaths": 23.0, "total_d": 1747.0, "date": "2020-04-24"}, {"deaths": 51.0, "total_d": 1724.0, "date": "2020-04-23"}, {"deaths": 59.0, "total_d": 1673.0, "date": "2020-04-22"}, {"deaths": 266.0, "total_d": 1614.0, "date": "2020-04-21"}, {"deaths": 72.0, "total_d": 1348.0, "date": "2020-04-20"}, {"deaths": 234.0, "total_d": 1276.0, "date": "2020-04-19"}, {"deaths": 121.0, "total_d": 1042.0, "date": "2020-04-18"}, {"deaths": 80.0, "total_d": 921.0, "date": "2020-04-17"}, {"deaths": 62.0, "total_d": 841.0, "date": "2020-04-16"}, {"deaths": 88.0, "total_d": 779.0, "date": "2020-04-15"}, {"deaths": 102.0, "total_d": 691.0, "date": "2020-04-14"}, {"deaths": 32.0, "total_d": 589.0, "date": "2020-04-13"}, {"deaths": 54.0, "total_d": 557.0, "date": "2020-04-12"}, {"deaths": 85.0, "total_d": 503.0, "date": "2020-04-11"}, {"deaths": 73.0, "total_d": 418.0, "date": "2020-04-10"}, {"deaths": 27.0, "total_d": 345.0, "date": "2020-04-09"}, {"deaths": 71.0, "total_d": 318.0, "date": "2020-04-08"}, {"deaths": 68.0, "total_d": 247.0, "date": "2020-04-07"}, {"deaths": 28.0, "total_d": 179.0, "date": "2020-04-06"}, {"deaths": 15.0, "total_d": 151.0, "date": "2020-04-05"}, {"deaths": 34.0, "total_d": 136.0, "date": "2020-04-04"}, {"deaths": 12.0, "total_d": 102.0, "date": "2020-04-03"}, {"deaths": 16.0, "total_d": 90.0, "date": "2020-04-02"}, {"deaths": 11.0, "total_d": 74.0, "date": "2020-04-01"}, {"deaths": 13.0, "total_d": 63.0, "date": "2020-03-31"}, {"deaths": 9.0, "total_d": 50.0, "date": "2020-03-30"}, {"deaths": 7.0, "total_d": 41.0, "date": "2020-03-29"}, {"deaths": 12.0, "total_d": 34.0, "date": "2020-03-28"}, {"deaths": 4.0, "total_d": 22.0, "date": "2020-03-27"}, {"deaths": 3.0, "total_d": 18.0, "date": "2020-03-26"}, {"deaths": 7.0, "total_d": 15.0, "date": "2020-03-25"}, {"deaths": 2.0, "total_d": 8.0, "date": "2020-03-24"}, {"deaths": 2.0, "total_d": 6.0, "date": "2020-03-23"}, {"deaths": 2.0, "total_d": 4.0, "date": "2020-03-22"}, {"deaths": 1.0, "total_d": 2.0, "date": "2020-03-21"}, {"deaths": 0.0, "total_d": 1.0, "date": "2020-03-20"}, {"deaths": 1.0, "total_d": 1.0, "date": "2020-03-19"}, {"deaths": 0.0, "total_d": 0.0, "date": "2020-03-18"}, {"deaths": 0.0, "total_d": 0.0, "date": "2020-03-17"}, {"deaths": 0.0, "total_d": 0.0, "date": "2020-03-16"}, {"deaths": 0.0, "total_d": 0.0, "date": "2020-03-15"}, {"deaths": 0.0, "total_d": 0.0, "date": "2020-03-14"}, {"deaths": 0.0, "total_d": 0.0, "date": "2020-03-13"}, {"deaths": 0.0, "total_d": 0.0, "date": "2020-03-12"}, {"deaths": 0.0, "total_d": 0.0, "date": "2020-03-11"}, {"deaths": 0.0, "total_d": 0.0, "date": "2020-03-10"}, {"deaths": 0.0, "total_d": 0.0, "date": "2020-03-09"}, {"deaths": 0.0, "total_d": 0.0, "date": "2020-03-08"}, {"deaths": 0.0, "total_d": 0.0, "date": "2020-03-07"}, {"deaths": 0.0, "total_d": 0.0, "date": "2020-03-06"}, {"deaths": 0.0, "total_d": 0.0, "date": "2020-03-05"}, {"deaths": 0.0, "total_d": 0.0, "date": "2020-03-04"}, {"deaths": 0.0, "total_d": 0.0, "date": "2020-03-03"}, {"deaths": 0.0, "total_d": 0.0, "date": "2020-03-02"}, {"deaths": 0.0, "total_d": 0.0, "date": "2020-03-01"}, {"deaths": 0.0, "total_d": 0.0, "date": "2020-02-29"}, {"deaths": 0.0, "total_d": 0.0, "date": "2020-02-28"}, {"deaths": 0.0, "total_d": 0.0, "date": "2020-02-27"}, {"deaths": 0.0, "total_d": 0.0, "date": "2020-02-26"}, {"deaths": 0.0, "total_d": 0.0, "date": "2020-02-25"}, {"deaths": 0.0, "total_d": 0.0, "date": "2020-02-24"}, {"deaths": 0.0, "total_d": 0.0, "date": "2020-02-23"}, {"deaths": 0.0, "total_d": 0.0, "date": "2020-02-22"}, {"deaths": 0.0, "total_d": 0.0, "date": "2020-02-21"}, {"deaths": 0.0, "total_d": 0.0, "date": "2020-02-20"}, {"deaths": 0.0, "total_d": 0.0, "date": "2020-02-19"}, {"deaths": 0.0, "total_d": 0.0, "date": "2020-02-18"}, {"deaths": 0.0, "total_d": 0.0, "date": "2020-02-17"}, {"deaths": 0.0, "total_d": 0.0, "date": "2020-02-16"}, {"deaths": 0.0, "total_d": 0.0, "date": "2020-02-15"}, {"deaths": 0.0, "total_d": 0.0, "date": "2020-02-14"}, {"deaths": 0.0, "total_d": 0.0, "date": "2020-02-13"}, {"deaths": 0.0, "total_d": 0.0, "date": "2020-02-12"}, {"deaths": 0.0, "total_d": 0.0, "date": "2020-02-11"}, {"deaths": 0.0, "total_d": 0.0, "date": "2020-02-10"}, {"deaths": 0.0, "total_d": 0.0, "date": "2020-02-09"}, {"deaths": 0.0, "total_d": 0.0, "date": "2020-02-08"}, {"deaths": 0.0, "total_d": 0.0, "date": "2020-02-07"}, {"deaths": 0.0, "total_d": 0.0, "date": "2020-02-06"}, {"deaths": 0.0, "total_d": 0.0, "date": "2020-02-05"}, {"deaths": 0.0, "total_d": 0.0, "date": "2020-02-04"}], "projected": [{"deaths": 11.0, "total_d": 8133.0, "date": "2020-10-01"}, {"deaths": 11.0, "total_d": 8123.0, "date": "2020-09-30"}, {"deaths": 11.0, "total_d": 8112.0, "date": "2020-09-29"}, {"deaths": 11.0, "total_d": 8101.0, "date": "2020-09-28"}, {"deaths": 11.0, "total_d": 8091.0, "date": "2020-09-27"}, {"deaths": 11.0, "total_d": 8080.0, "date": "2020-09-26"}, {"deaths": 11.0, "total_d": 8069.0, "date": "2020-09-25"}, {"deaths": 11.0, "total_d": 8059.0, "date": "2020-09-24"}, {"deaths": 11.0, "total_d": 8048.0, "date": "2020-09-23"}, {"deaths": 11.0, "total_d": 8038.0, "date": "2020-09-22"}, {"deaths": 11.0, "total_d": 8027.0, "date": "2020-09-21"}, {"deaths": 11.0, "total_d": 8017.0, "date": "2020-09-20"}, {"deaths": 11.0, "total_d": 8006.0, "date": "2020-09-19"}, {"deaths": 11.0, "total_d": 7995.0, "date": "2020-09-18"}, {"deaths": 11.0, "total_d": 7985.0, "date": "2020-09-17"}, {"deaths": 11.0, "total_d": 7974.0, "date": "2020-09-16"}, {"deaths": 11.0, "total_d": 7964.0, "date": "2020-09-15"}, {"deaths": 11.0, "total_d": 7953.0, "date": "2020-09-14"}, {"deaths": 11.0, "total_d": 7942.0, "date": "2020-09-13"}, {"deaths": 11.0, "total_d": 7931.0, "date": "2020-09-12"}, {"deaths": 11.0, "total_d": 7921.0, "date": "2020-09-11"}, {"deaths": 11.0, "total_d": 7910.0, "date": "2020-09-10"}, {"deaths": 11.0, "total_d": 7899.0, "date": "2020-09-09"}, {"deaths": 11.0, "total_d": 7888.0, "date": "2020-09-08"}, {"deaths": 11.0, "total_d": 7877.0, "date": "2020-09-07"}, {"deaths": 11.0, "total_d": 7866.0, "date": "2020-09-06"}, {"deaths": 11.0, "total_d": 7855.0, "date": "2020-09-05"}, {"deaths": 11.0, "total_d": 7843.0, "date": "2020-09-04"}, {"deaths": 11.0, "total_d": 7832.0, "date": "2020-09-03"}, {"deaths": 11.0, "total_d": 7821.0, "date": "2020-09-02"}, {"deaths": 11.0, "total_d": 7809.0, "date": "2020-09-01"}, {"deaths": 11.0, "total_d": 7798.0, "date": "2020-08-31"}, {"deaths": 12.0, "total_d": 7787.0, "date": "2020-08-30"}, {"deaths": 12.0, "total_d": 7775.0, "date": "2020-08-29"}, {"deaths": 12.0, "total_d": 7763.0, "date": "2020-08-28"}, {"deaths": 12.0, "total_d": 7751.0, "date": "2020-08-27"}, {"deaths": 13.0, "total_d": 7739.0, "date": "2020-08-26"}, {"deaths": 13.0, "total_d": 7726.0, "date": "2020-08-25"}, {"deaths": 13.0, "total_d": 7714.0, "date": "2020-08-24"}, {"deaths": 13.0, "total_d": 7701.0, "date": "2020-08-23"}, {"deaths": 14.0, "total_d": 7687.0, "date": "2020-08-22"}, {"deaths": 14.0, "total_d": 7674.0, "date": "2020-08-21"}, {"deaths": 14.0, "total_d": 7660.0, "date": "2020-08-20"}, {"deaths": 14.0, "total_d": 7646.0, "date": "2020-08-19"}, {"deaths": 15.0, "total_d": 7632.0, "date": "2020-08-18"}, {"deaths": 15.0, "total_d": 7617.0, "date": "2020-08-17"}, {"deaths": 15.0, "total_d": 7602.0, "date": "2020-08-16"}, {"deaths": 16.0, "total_d": 7587.0, "date": "2020-08-15"}, {"deaths": 16.0, "total_d": 7571.0, "date": "2020-08-14"}, {"deaths": 16.0, "total_d": 7555.0, "date": "2020-08-13"}, {"deaths": 17.0, "total_d": 7539.0, "date": "2020-08-12"}, {"deaths": 17.0, "total_d": 7522.0, "date": "2020-08-11"}, {"deaths": 17.0, "total_d": 7505.0, "date": "2020-08-10"}, {"deaths": 18.0, "total_d": 7488.0, "date": "2020-08-09"}, {"deaths": 18.0, "total_d": 7470.0, "date": "2020-08-08"}, {"deaths": 19.0, "total_d": 7452.0, "date": "2020-08-07"}, {"deaths": 19.0, "total_d": 7433.0, "date": "2020-08-06"}, {"deaths": 19.0, "total_d": 7414.0, "date": "2020-08-05"}, {"deaths": 20.0, "total_d": 7395.0, "date": "2020-08-04"}, {"deaths": 20.0, "total_d": 7375.0, "date": "2020-08-03"}, {"deaths": 21.0, "total_d": 7355.0, "date": "2020-08-02"}, {"deaths": 21.0, "total_d": 7334.0, "date": "2020-08-01"}, {"deaths": 22.0, "total_d": 7313.0, "date": "2020-07-31"}, {"deaths": 22.0, "total_d": 7292.0, "date": "2020-07-30"}, {"deaths": 22.0, "total_d": 7270.0, "date": "2020-07-29"}, {"deaths": 23.0, "total_d": 7247.0, "date": "2020-07-28"}, {"deaths": 23.0, "total_d": 7224.0, "date": "2020-07-27"}, {"deaths": 24.0, "total_d": 7201.0, "date": "2020-07-26"}, {"deaths": 24.0, "total_d": 7178.0, "date": "2020-07-25"}, {"deaths": 24.0, "total_d": 7154.0, "date": "2020-07-24"}, {"deaths": 25.0, "total_d": 7129.0, "date": "2020-07-23"}, {"deaths": 25.0, "total_d": 7104.0, "date": "2020-07-22"}, {"deaths": 26.0, "total_d": 7079.0, "date": "2020-07-21"}, {"deaths": 26.0, "total_d": 7053.0, "date": "2020-07-20"}, {"deaths": 26.0, "total_d": 7027.0, "date": "2020-07-19"}, {"deaths": 27.0, "total_d": 7001.0, "date": "2020-07-18"}, {"deaths": 27.0, "total_d": 6974.0, "date": "2020-07-17"}, {"deaths": 28.0, "total_d": 6947.0, "date": "2020-07-16"}, {"deaths": 28.0, "total_d": 6919.0, "date": "2020-07-15"}, {"deaths": 28.0, "total_d": 6891.0, "date": "2020-07-14"}, {"deaths": 29.0, "total_d": 6863.0, "date": "2020-07-13"}, {"deaths": 29.0, "total_d": 6835.0, "date": "2020-07-12"}, {"deaths": 29.0, "total_d": 6806.0, "date": "2020-07-11"}, {"deaths": 29.0, "total_d": 6777.0, "date": "2020-07-10"}, {"deaths": 29.0, "total_d": 6748.0, "date": "2020-07-09"}, {"deaths": 29.0, "total_d": 6718.0, "date": "2020-07-08"}, {"deaths": 30.0, "total_d": 6689.0, "date": "2020-07-07"}, {"deaths": 30.0, "total_d": 6659.0, "date": "2020-07-06"}, {"deaths": 30.0, "total_d": 6630.0, "date": "2020-07-05"}, {"deaths": 30.0, "total_d": 6600.0, "date": "2020-07-04"}, {"deaths": 30.0, "total_d": 6570.0, "date": "2020-07-03"}, {"deaths": 30.0, "total_d": 6540.0, "date": "2020-07-02"}, {"deaths": 30.0, "total_d": 6510.0, "date": "2020-07-01"}, {"deaths": 30.0, "total_d": 6480.0, "date": "2020-06-30"}, {"deaths": 30.0, "total_d": 6450.0, "date": "2020-06-29"}, {"deaths": 30.0, "total_d": 6420.0, "date": "2020-06-28"}, {"deaths": 24.0, "total_d": 6603.0, "date": "2020-06-27"}, {"deaths": 22.0, "total_d": 6579.0, "date": "2020-06-26"}, {"deaths": 39.0, "total_d": 6557.0, "date": "2020-06-25"}, {"deaths": 54.0, "total_d": 6518.0, "date": "2020-06-24"}], "sum": {"last_update": "2020_06_27"}}